pydgrid/ClearnessIndexTPM.csv
pydgrid/__init__.py
pydgrid/electric.py
pydgrid/image.html
pydgrid/lines.py
pydgrid/log.txt
pydgrid/pf.py
pydgrid/plot_bokeh.py
pydgrid/pydgrid.py
pydgrid/simu.py
pydgrid/solar.py
pydgrid/transformers.py
pydgrid/translations.py
pydgrid/vsclosses.py
pydgrid/tools/__init__.py
pydgrid/tools/load_shapes_list.json
pydgrid/tools/log.txt
pydgrid/tools/opendss_tools.py
pydgrid/tools/out.json
pydgrid/tools/spreadsheet.py
pydgrid-0.5.3.dist-info/COPYING
pydgrid-0.5.3.dist-info/LICENSE
pydgrid-0.5.3.dist-info/WHEEL
pydgrid-0.5.3.dist-info/METADATA
pydgrid-0.5.3.dist-info/RECORD
