Metadata-Version: 2.1
Name: pydgrid
Version: 0.5.3
Summary: Created on Fri Jun 16 12:54:49 2017
Home-page: https://personal.us.es/jmmauricio/
License: UNKNOWN
Author: Juan Manuel Mauricio
Author-email: jmmauricio@us.es
Classifier: License :: OSI Approved :: MIT License
